MANIFEST.in
README.rst
setup.py
TheRiddler.egg-info/PKG-INFO
TheRiddler.egg-info/SOURCES.txt
TheRiddler.egg-info/dependency_links.txt
TheRiddler.egg-info/requires.txt
TheRiddler.egg-info/top_level.txt
misc/CHANGES.txt
misc/CONTRIBUTING.md
misc/LICENSE.txt
misc/README.md
misc/cx_Freeze_stuff/CHEAT_SHEET.txt
misc/cx_Freeze_stuff/Installing_cx_Freeze_6.0b1.jpg
misc/cx_Freeze_stuff/TheRiddler_cx_Freeze_dir.jpg
misc/cx_Freeze_stuff/cx_Freeze-6.0b1.tar.gz
misc/cx_Freeze_stuff/setup.py
theriddler/__init__.py
theriddler/__main__.py
theriddler/data/brushed_r.ico
theriddler/data/apesanteur/cool_stuff.txt
theriddler/data/apesanteur/flying.jpg
theriddler/data/bete/asdf.txt
theriddler/data/bete/calcul.jpg
theriddler/data/devoilement/aid.url
theriddler/data/devoilement/readme.jpg
theriddler/data/enroulement/cx_Freeze.url
theriddler/data/enroulement/outro.jpg
theriddler/data/habitudes/bad_habits.jpg
theriddler/data/habitudes/broken_script.py
theriddler/data/interieur/babuschka.jpg
theriddler/data/interieur/cool_stuff.txt
theriddler/data/inverse/bib.png
theriddler/data/inverse/upsidedown.png
theriddler/data/jeux/gtg.py
theriddler/data/jeux/space.jpg
theriddler/data/motif/bodyguards.txt
theriddler/data/motif/candles.jpg
theriddler/data/progres/.pypirc
theriddler/data/progres/diy.jpg
theriddler/data/raccourci/put_me_somewhere.jpg
theriddler/data/raccourci/starwars.txt
theriddler/data/rarete/book.jpg
theriddler/data/rarete/mess.txt
theriddler/data/recherche/nose.jpg
theriddler/data/recherche/reST.url
theriddler/data/salade/character_shift.jpg
theriddler/data/salade/gibberish.rst
theriddler/data/scelle/htwg_website.jpg
theriddler/data/scelle/locked.zip
theriddler/data/secrets/help.jpg
theriddler/data/secrets/manual.jpg
theriddler/data/vide/gobackandlearnstuff.txt
theriddler/data/vide/noriddle.png
theriddler/riddles/__init__.py
theriddler/riddles/apesanteur.py
theriddler/riddles/bete.py
theriddler/riddles/devoilement.py
theriddler/riddles/enroulement.py
theriddler/riddles/habitudes.py
theriddler/riddles/interieur.py
theriddler/riddles/inverse.py
theriddler/riddles/jeux.py
theriddler/riddles/motif.py
theriddler/riddles/progres.py
