Metadata-Version: 1.1
Name: TheRiddler
Version: 0.1.3
Summary: Sample project for the lecture "Introduction to Python" 
Home-page: UNKNOWN
Author: Etienne Martin
Author-email: etienne.martin@htwg-konstanz.de
License: MIT
Keywords: theriddler theRiddler RIDDLER Riddler riddler riddles sample learning quiz
Platform: UNKNOWN
Classifier: Development Status :: 3 - Alpha
Classifier: License :: OSI Approved :: MIT License
Classifier: Programming Language :: Python :: 3.6
Classifier: Intended Audience :: Education
Classifier: Natural Language :: English
